canvas-tools/__init__.py
canvas-tools/canvas_group_csv.py
canvas_tools/__init__.py
canvas_tools/canvas_group_csv.py
canvas_tools/download_annotated_pdf.py
canvas_tools/download_quiz_questions.py
canvas_tools/get_quiz_answers.py
canvas_tools-0.0.4.dist-info/LICENSE
canvas_tools-0.0.4.dist-info/METADATA
canvas_tools-0.0.4.dist-info/WHEEL
canvas_tools-0.0.4.dist-info/entry_points.txt
canvas_tools-0.0.4.dist-info/top_level.txt
canvas_tools-0.0.4.dist-info/RECORD
