Metadata-Version: 2.1
Name: canvas-tools
Version: 0.0.4
Summary: A set of tools for working with Canvas.
Home-page: https://github.com/alanzchen/Canvas-Tools
Author: Alan Chen
Author-email: me@zenan.ch
License: UNKNOWN
Platform: UNKNOWN
Classifier: Programming Language :: Python :: 3
Classifier: License :: OSI Approved :: MIT License
Classifier: Operating System :: OS Independent
Requires-Python: >=3.6
Requires-Dist: requests
Requires-Dist: pandas
Requires-Dist: canvasapi
Requires-Dist: bs4
